turbot/__init__.py
turbot/_version.py
turbot/assets/alembic.ini
turbot/assets/art.csv
turbot/assets/bugs.csv
turbot/assets/fish.csv
turbot/assets/fossils.csv
turbot/assets/songs.csv
turbot/assets/strings.yaml
turbot/assets.py
turbot/data.py
turbot/versions/env.py
turbot/versions/script.py.mako
turbot/versions/versions/1afdca2a2389_adds_relationships.py
turbot/versions/versions/33940279af35_keep_track_of_authorized_channels_per_.py
turbot/versions/versions/9b107d322c46_use_bigint_for_author_ids.py
turbot/versions/versions/a5d26dbfc9a3_support_longer_timestamps.py
turbot/versions/versions/cb8aa87d74cb_initial_revision.py
turnips/__init__.py
turnips/archipelago.py
turnips/example.py
turnips/markov.py
turnips/meta.py
turnips/model.py
turnips/modifier.py
turnips/multi.py
turnips/plots.py
turnips/price.py
turnips/script.py
turnips/ttime.py
turbot-7.5.2.dist-info/entry_points.txt
turbot-7.5.2.dist-info/LICENSE.md
turbot-7.5.2.dist-info/WHEEL
turbot-7.5.2.dist-info/METADATA
turbot-7.5.2.dist-info/RECORD
