Metadata-Version: 2.1
Name: turbot
Version: 7.5.2
Summary: Provides a Discord client and utilities for everything Animal Crossing: New Horizons.
Home-page: https://github.com/theastropath/turbot
License: MIT
Keywords: discord,turnip,bot,animal crossing,new horizons
Author: TheAstropath
Author-email: theastropath@gmail.com
Requires-Python: >=3.7,<4
Classifier: Development Status :: 4 - Beta
Classifier: Intended Audience :: End Users/Desktop
Classifier: License :: OSI Approved :: MIT License
Classifier: Programming Language :: Python :: 3
Classifier: Programming Language :: Python :: 3.7
Classifier: Programming Language :: Python :: 3.8
Classifier: Topic :: Communications :: Chat
Classifier: Topic :: Games/Entertainment :: Simulation
Requires-Dist: alembic (>=1.4.2,<2.0.0)
Requires-Dist: click (>=7.1.2,<8.0.0)
Requires-Dist: discord-py (>=1.3.3,<2.0.0)
Requires-Dist: dunamai (>=1.2.0,<2.0.0)
Requires-Dist: humanize (>=2.4.0,<3.0.0)
Requires-Dist: hupper (>=1.10.2,<2.0.0)
Requires-Dist: matplotlib (>=3.2.2,<4.0.0)
Requires-Dist: numpy (>=1.18.5,<2.0.0)
Requires-Dist: pandas (>=1.0.5,<2.0.0)
Requires-Dist: psycopg2-binary (>=2.8.5,<3.0.0)
Requires-Dist: pydantic (>=1.5.1,<2.0.0)
Requires-Dist: python-dateutil (>=2.8.1,<3.0.0)
Requires-Dist: pytz (>=2020.1,<2021.0)
Requires-Dist: pyyaml (>=5.3.1,<6.0.0)
Requires-Dist: sqlalchemy (>=1.3.17,<2.0.0)
Requires-Dist: unidecode (>=1.1.1,<2.0.0)
Project-URL: Repository, https://github.com/theastropath/turbot
